deepdanbooru/__init__.py
deepdanbooru/__main__.py
deepdanbooru/gradcam.py
deepdanbooru/commands/__init__.py
deepdanbooru/commands/convert_to_tflite.py
deepdanbooru/commands/create_project.py
deepdanbooru/commands/download_tags.py
deepdanbooru/commands/evaluate.py
deepdanbooru/commands/evaluate_project.py
deepdanbooru/commands/grad_cam.py
deepdanbooru/commands/make_training_database.py
deepdanbooru/commands/train_project.py
deepdanbooru/data/__init__.py
deepdanbooru/data/dataset.py
deepdanbooru/data/dataset_wrapper.py
deepdanbooru/extra/__init__.py
deepdanbooru/image/__init__.py
deepdanbooru/io/__init__.py
deepdanbooru/model/__init__.py
deepdanbooru/model/resnet.py
deepdanbooru/model/layers/__init__.py
deepdanbooru/model/losses/__init__.py
deepdanbooru/project/__init__.py
deepdanbooru/project/project.py
deepdanbooru/train/__init__.py
deepdanbooru-1.0.4.dist-info/licenses/LICENSE
deepdanbooru-1.0.4.dist-info/METADATA
deepdanbooru-1.0.4.dist-info/WHEEL
deepdanbooru-1.0.4.dist-info/entry_points.txt
deepdanbooru-1.0.4.dist-info/top_level.txt
deepdanbooru-1.0.4.dist-info/RECORD
