Metadata-Version: 2.4
Name: deepdanbooru
Version: 1.0.4
Summary: DeepDanbooru is AI based multi-label girl image classification system, implemented by using TensorFlow.
Home-page: https://github.com/KichangKim/DeepDanbooru
Author: Kichang Kim
Author-email: admin@kanotype.net
License: MIT
Keywords: icq bot framework async python
Classifier: Programming Language :: Python :: 3
Classifier: License :: OSI Approved :: MIT License
Classifier: Operating System :: OS Independent
Requires-Python: >=3.6
License-File: LICENSE
Requires-Dist: Click>=8.1.7
Requires-Dist: numpy>=1.26.4
Requires-Dist: scikit-image>=0.24.0
Requires-Dist: requests>=2.32.3
Requires-Dist: six>=1.16.0
Provides-Extra: test
Requires-Dist: pytest; extra == "test"
Requires-Dist: flake8; extra == "test"
Requires-Dist: mypy; extra == "test"
Provides-Extra: tensorflow
Requires-Dist: tensorflow>=2.17.0; extra == "tensorflow"
Requires-Dist: tensorflow-io>=0.31.0; extra == "tensorflow"
Dynamic: license-file
